Workbook

Sheet README
B1: Namma Kural — Scale-Readiness Audit
B2: Branch phase1_flutter · target 100 MLA offices and 100,000 citizens
B4: Audit date | C4: 2026-09-17
B5: Scope audited | C5: backend/ (4,570 LOC) · mobile/lib (16,034 LOC) · SQLite schema · frontend admin dashboard
B6: Explicitly excluded | C6: PWA and the citizen/coordinator web frontend, except the admin dashboard
B7: Method | C7: Line-by-line read of every backend module and router, the Flutter data/state/domain layers and screens, the live seed database schema, and the admin console data layer
B8: Findings | C8: 90 across 10 epics and 10 sprints
B10: How to use this workbook
B11: Findings is the working sheet — set Status and Owner there and everything else follows. Dashboard, Epics and Sprints read from it automatically, so they stay correct as the team updates Status.
B12: Status values: Open, In Progress, Blocked, In Review, Done, Won't Fix. Pick from the dropdown so the rollups keep working.
B13: Priority score = severity weight (Critical 100, High 60, Medium 30, Low 10) multiplied by likelihood (Certain 1.0, Likely 0.8, Possible 0.5, Unlikely 0.25). Sort on it when sequencing work inside a sprint.
B15: The three things that decide the programme
B16: 1. Nothing is authenticated. Login mints no token; a caller asserts their identity in a form field. The entire coordinator surface is mounted with no auth dependency, and public grievance payloads carry every reporter's name and mobile number.
B17: 2. The data layer cannot reach this scale. One SQLite file, zero indexes on the issues table, every list query a full table scan, and the admin console downloads the whole table into the browser.
B18: 3. The system is built for 16 Chennai constituencies, not 100. Boundaries are Greater Chennai only, and a report outside them is refused outright — so 99 of the 100 target offices cannot receive a single grievance today.
B20: What this audit did not do
B21: No source file was modified and nothing was pushed. No penetration testing or live probing was performed against any deployed environment — every finding is from reading the code on this branch.

Sheet Dashboard
B2: Audit Dashboard
B3: Live counts — they update as Status changes on the Findings sheet.
B5: By severity
B6: Critical | C6: High | D6: Medium | E6: Low | F6: Total
B7: =COUNTIF(Findings!$D$2:$D$91,"Critical") | C7: =COUNTIF(Findings!$D$2:$D$91,"High") | D7: =COUNTIF(Findings!$D$2:$D$91,"Medium") | E7: =COUNTIF(Findings!$D$2:$D$91,"Low") | F7: =COUNTA(Findings!$A$2:$A$91)
B9: By status
B10: Open | C10: In Progress | D10: Blocked | E10: In Review | F10: Done
B11: =COUNTIF(Findings!$Q$2:$Q$91,"Open") | C11: =COUNTIF(Findings!$Q$2:$Q$91,"In Progress") | D11: =COUNTIF(Findings!$Q$2:$Q$91,"Blocked") | E11: =COUNTIF(Findings!$Q$2:$Q$91,"In Review") | F11: =COUNTIF(Findings!$Q$2:$Q$91,"Done")
B13: Effort (person-days)
B14: Total | C14: Critical | D14: Remaining | E14: Done | F14: % complete
B15: =SUM(Findings!$P$2:$P$91) | C15: =SUMIF(Findings!$D$2:$D$91,"Critical",Findings!$P$2:$P$91) | D15: =SUMIFS(Findings!$P$2:$P$91,Findings!$Q$2:$Q$91,"<>Done") | E15: =SUMIFS(Findings!$P$2:$P$91,Findings!$Q$2:$Q$91,"Done") | F15: =IF(B15=0,0,E15/B15)
B18: By finding type
B19: Type | C19: Count
B20: Compliance | C20: 6
B21: Correctness | C21: 10
B22: Cost | C22: 4
B23: Maintainability | C23: 3
B24: Performance | C24: 17
B25: Privacy | C25: 3
B26: Quality | C26: 2
B27: Reliability | C27: 8
B28: Scalability | C28: 10
B29: Security | C29: 27
B32: Highest-priority findings
B33: ID | C33: Severity | D33: Score | E33: Finding
B34: F001 | C34: Critical | D34: 100 | E34: Login issues no session token — the entire API is unauthenticated
B35: F002 | C35: Critical | D35: 100 | E35: Coordinator router mounted with no auth dependency
B36: F003 | C36: Critical | D36: 100 | E36: _authorize() returns early when the coordinator field is blank
B37: F014 | C37: Critical | D37: 100 | E37: serialize_issue returns the reporter's phone, name and account id on public endpoints
B38: F015 | C38: Critical | D38: 100 | E38: Single shared admin account with a default password in source
B39: F018 | C39: Critical | D39: 100 | E39: Single-file SQLite on one volume is the whole datastore
B40: F019 | C40: Critical | D40: 100 | E40: Zero indexes on the issues table
B41: F027 | C41: Critical | D41: 100 | E41: GET /api/admin/issues returns the entire table with no pagination
B42: F028 | C42: Critical | D42: 100 | E42: /api/issues/nearby scans every non-SUBMITTED row and computes Haversine in Python
B43: F029 | C43: Critical | D43: 100 | E43: Blocking Gemini and geocoding calls inside an async endpoint block the event loop
B44: F031 | C44: Critical | D44: 100 | E44: coordinator-performance is an N+1 that scans the issues table once per coordinator
B45: F036 | C45: Critical | D45: 100 | E45: Uploaded media lives on a local volume, not object storage
... B48: F051 | C48: Critical | D48: 100 | E48: Constituency map is hardcoded to 16 Chennai assembly constituencies

Sheet Findings
A1: ID | B1: Epic | C1: Sprint | D1: Severity | E1: Likelihood | F1: Priority | G1: Type | H1: Area | I1: Component | J1: File | K1: Line | L1: Finding | M1: Detail | N1: Impact at 100 MLA / 1 lakh citizens | O1: Recommendation | P1: Effort (days) | Q1: Status | R1: Owner | S1: Target date | T1: Notes
A2: F001 | B2: E1 | C2: S1 | D2: Critical | E2: Certain | F2: 100 | G2: Security | H2: Backend | I2: Auth | J2: backend/routers/auth.py | K2: 149-190 | L2: Login issues no session token — the entire API is unauthenticated | M2: POST /api/auth/login and /api/auth/coordinator/login both return a plain profile JSON. No token, cookie, JWT or session is ever minted. Every subsequent call identifies the caller by a user_id or coordinator username sent as a form field. | N2: Any person with the API base URL can act as any citizen or any coordinator. With 100k accounts and 100 MLA offices this is a total authorisation bypass across the whole product. | O2: Mint a short-lived signed access token at login (JWT or the existing HMAC scheme from admin_auth.py), return it, require it on every non-public route, and derive the actor identity from the token — never from a request field. | P2: 8 | Q2: Open
A3: F002 | B3: E1 | C3: S1 | D3: Critical | E3: Certain | F3: 100 | G3: Security | H3: Backend | I3: Coordinator API | J3: backend/main.py | K3: 225 | L3: Coordinator router mounted with no auth dependency | M3: app.include_router(coordinator.router) has no Depends(require_*). Every endpoint under /api/coordinator — verify, transfer, escalate, redirect, close, mark_false, ward listing, timeline — is publicly reachable. | N3: Anyone can drive any grievance in any ward through its entire lifecycle, close tickets with fake evidence, or mark real complaints as false petitions. At 100 constituencies this destroys the integrity of the whole redressal record. | O3: Gate the router with a coordinator-token dependency the same way the admin router is gated, and resolve the acting coordinator from the token. | P3: 3 | Q3: Open
A4: F003 | B4: E1 | C4: S1 | D4: Critical | E4: Certain | F4: 100 | G4: Security | H4: Backend | I4: Coordinator API | J4: backend/routers/coordinator.py | K4: 76-98 | L4: _authorize() returns early when the coordinator field is blank | M4: The guard opens with: who = (coordinator or '').strip(); if not who: return. It is documented as back-compat for older APKs that send nothing. | N4: The only ownership check in the coordinator surface is bypassed by omitting one form field. Every action endpoint is fully open even to a caller who knows nothing about the system. | O4: Make the actor mandatory and read it from the token. Force-upgrade old APK builds with a minimum-version gate rather than keeping the hole open. | P4: 2 | Q4: Open
A5: F014 | B5: E6 | C5: S1 | D5: Critical | E5: Certain | F5: 100 | G5: Privacy | H5: Backend | I5: Serialization | J5: backend/utils.py | K5: 163-187 | L5: serialize_issue returns the reporter's phone, name and account id on public endpoints | M5: serialize_issue does dict(row) over the whole issues row, which includes phone, name and created_by, and is used by the unauthenticated GET /api/issues/ward/{n}, /nearby and /supported/{id}. | N5: Anyone can harvest the name, mobile number and account id of every citizen who has ever reported a grievance. At 100k citizens this is a mass personal-data breach and a DPDP Act 2023 violation with real penalty exposure. | O5: Split into a public projection (no phone, no name, no created_by) and an internal one. Default to the public shape and opt in explicitly on authenticated staff routes. | P5: 2 | Q5: Open
A6: F015 | B6: E1 | C6: S2 | D6: Critical | E6: Certain | F6: 100 | G6: Security | H6: Backend | I6: Admin | J6: backend/admin_auth.py | K6: 36 | L6: Single shared admin account with a default password in source | M6: ADMIN_PASSWORD defaults to 'nammakural'. One username serves the whole console; there is no per-office account and no roles. | N6: 100 MLA offices would share one credential. No office can be revoked individually, and nothing records which office performed which action. | O6: Per-office admin accounts with hashed passwords and roles, bound to a constituency. Remove the default password; refuse to boot without one set. | P6: 5 | Q6: Open
A7: F018 | B7: E2 | C7: S3 | D7: Critical | E7: Certain | F7: 100 | G7: Scalability | H7: Database | I7: Engine | J7: backend/database.py | K7: 11-22 | L7: Single-file SQLite on one volume is the whole datastore | M7: DB_PATH resolves to a single SQLite file on a Railway /data volume. sqlite3 with check_same_thread=False, one connection opened and closed per request, no WAL mode, no pooling. | N7: SQLite serialises writes with a global lock. At 100k citizens the reporting, upvoting and coordinator-action write load will lock contend continuously, and the design cannot scale past one process or one machine. | O7: Migrate to managed PostgreSQL with PgBouncer. Keep SQLite only for local development behind the same repository interface. | P7: 15 | Q7: Open
A8: F019 | B8: E2 | C8: S3 | D8: Critical | E8: Certain | F8: 100 | G8: Performance | H8: Database | I8: Indexes | J8: backend/database.py | K8: 61-76 | L8: Zero indexes on the issues table | M8: Verified against the shipped seed DB: the only index on issues is the primary-key autoindex. Queries filter on ward_no, status, created_by, assigned_coordinator, department and zone — all unindexed. | N8: Every ward feed, every history load, every coordinator queue and every admin filter is a full table scan. At 100k+ rows with 100k users polling, the database is saturated by scans alone. | O8: Add composite indexes: (ward_no, status, created_at), (created_by, created_at), (assigned_coordinator, status), (status, upvotes), (department). Verify with EXPLAIN QUERY PLAN. | P8: 2 | Q8: Open
A9: F027 | B9: E3 | C9: S4 | D9: Critical | E9: Certain | F9: 100 | G9: Performance | H9: Backend | I9: Admin API | J9: backend/routers/admin.py | K9: 33-104 | L9: GET /api/admin/issues returns the entire table with no pagination | M9: The endpoint builds an optional WHERE clause, runs SELECT * with no LIMIT, serialises every row in Python and sorts the resulting list in Python. | N9: This is the single endpoint the whole console reads. At 100k+ grievances it is a multi-hundred-megabyte JSON response per page load, per operator, across 100 offices. It will time out or exhaust server memory. | O9: Add cursor pagination (limit/after), push sorting and filtering into indexed SQL, and return a lean projection rather than SELECT *. | P9: 5 | Q9: Open
A10: F028 | B10: E3 | C10: S4 | D10: Critical | E10: Certain | F10: 100 | G10: Performance | H10: Backend | I10: Citizen API | J10: backend/routers/issues.py | K10: 237-257 | L10: /api/issues/nearby scans every non-SUBMITTED row and computes Haversine in Python | M10: The handler loads all rows, then loops computing haversine_m per row before filtering by radius. | N10: The map is the app's landing surface. At 100k grievances and 100k users this is O(N) CPU per map open — the single hottest and most expensive path in the product. | O10: Pre-filter with a bounding box in indexed SQL, then refine. On PostGIS use ST_DWithin with a GiST index. | P10: 3 | Q10: Open
A11: F029 | B11: E3 | C11: S4 | D11: Critical | E11: Certain | F11: 100 | G11: Performance | H11: Backend | I11: Report path | J11: backend/routers/issues.py | K11: 59-72, 110-146 | L11: Blocking Gemini and geocoding calls inside an async endpoint block the event loop | M11: report_issue is declared async def but calls process_audio(), check_duplicate(), classify_department() and reverse_geocode() — all synchronous network calls taking seconds — directly on the event loop. | N11: Every report stalls the entire server process for the duration of several Gemini round trips. Under concurrent load from 100k citizens the API effectively serialises on AI latency. | O11: Accept the report immediately, persist it, and process transcription, duplicate detection and routing on a background worker queue (Celery/RQ/arq). Notify the client when enrichment completes. | P11: 8 | Q11: Open
A12: F031 | B12: E3 | C12: S4 | D12: Critical | E12: Certain | F12: 100 | G12: Performance | H12: Backend | I12: Admin API | J12: backend/routers/admin.py | K12: 360-407 | L12: coordinator-performance is an N+1 that scans the issues table once per coordinator | M12: For each coordinator the handler runs SELECT * FROM issues WHERE LOWER(assigned_coordinator) = ?. The LOWER() call also defeats any index. | N12: With 100 offices at roughly 5 coordinators each, one dashboard load triggers ~500 full table scans over 100k+ rows. This alone can take the database down. | O12: Replace with a single GROUP BY aggregate query. Store usernames already normalised so the index is usable. | P12: 2 | Q12: Open
A13: F036 | B13: E3 | C13: S4 | D13: Critical | E13: Certain | F13: 100 | G13: Scalability | H13: Backend | I13: Storage | J13: backend/utils.py | K13: 19-26 | L13: Uploaded media lives on a local volume, not object storage | M13: UPLOAD_DIR is a directory on the same volume as the database, served by the application process. | N13: Every photo, voice note and petition from 100k citizens accumulates on one disk with no CDN. Storage is finite, the app process becomes a file server, and horizontal scaling is impossible. | O13: Move to S3-compatible object storage with presigned upload URLs and CDN delivery. | P13: 5 | Q13: Open
... A91: F073 | B91: E8 | C91: S4 | D91: Low | E91: Unlikely | F91: 2.5 | G91: Correctness | H91: Mobile | I91: API client | J91: mobile/lib/data/dio_api_client.dart | K91: 99-102 | L91: Query string is built by interpolation without URL encoding | M91: fetchCoordinatorWardIssues concatenates the coordinator and sort values straight into the path. | N91: A username containing a reserved character produces a malformed request. Minor now because usernames are constrained, but it is a latent correctness bug. | O91: Pass values through queryParameters so Dio encodes them. | P91: 1 | Q91: Open

Sheet Epics
A1: Epic | B1: Name | C1: Goal | D1: Why this exists at this scale | E1: Findings | F1: Critical | G1: High | H1: Effort (days) | I1: Done | J1: % complete
A2: E1 | B2: Identity & Access Control | C2: Every API call proves who is calling, and can only touch its own data. | D2: Today a caller asserts their identity as a plain form field. Nothing is verified. At 100k citizens and 100 MLA offices this is the difference between a working system and an open database. | E2: 16 | F2: 10 | G2: 6 | H2: 38 | I2: =COUNTIFS(Findings!$B$2:$B$91,$A2,Findings!$Q$2:$Q$91,"Done") | J2: =IF($E2=0,0,$I2/$E2)
A3: E2 | B3: Data Platform & Persistence | C3: Move off single-file SQLite to a concurrent, indexed, backed-up datastore. | D3: One SQLite file on one Railway volume, with zero indexes on the issues table, cannot serve 100k citizens. Every list query is a full table scan today. | E3: 10 | F3: 3 | G3: 5 | H3: 36 | I3: =COUNTIFS(Findings!$B$2:$B$91,$A3,Findings!$Q$2:$Q$91,"Done") | J3: =IF($E3=0,0,$I3/$E3)
A4: E3 | B4: API Scalability & Performance | C4: Pagination, indexed filters, non-blocking I/O and caching on every hot path. | D4: The dashboard loads the entire issues table into the browser; the map scans every row in Python; Gemini calls block the event loop. | E4: 19 | F4: 8 | G4: 8 | H4: 54 | I4: =COUNTIFS(Findings!$B$2:$B$91,$A4,Findings!$Q$2:$Q$91,"Done") | J4: =IF($E4=0,0,$I4/$E4)
A5: E4 | B5: Notification & Realtime Delivery | C5: Replace 15/20-second client polling with push-first delivery. | D5: Two pollers per device at 100k devices is roughly 11,000 requests/second of pure overhead before a single citizen does anything. | E5: 6 | F5: 2 | G5: 3 | H5: 17 | I5: =COUNTIFS(Findings!$B$2:$B$91,$A5,Findings!$Q$2:$Q$91,"Done") | J5: =IF($E5=0,0,$I5/$E5)
A6: E5 | B6: Multi-Tenancy: 100 MLA Constituencies | C6: One deployment serving 100 constituencies, each seeing only its own data. | D6: The system is hardcoded to 16 Chennai ACs and Greater Chennai Corporation wards, with a single shared admin login. | E6: 7 | F6: 5 | G6: 2 | H6: 45 | I6: =COUNTIFS(Findings!$B$2:$B$91,$A6,Findings!$Q$2:$Q$91,"Done") | J6: =IF($E6=0,0,$I6/$E6)
A7: E6 | B7: Privacy, PII & Compliance (DPDP Act 2023) | C7: Citizen personal data is never exposed beyond who needs it, and is retained lawfully. | D7: Reporter name, phone number and account id are returned on public unauthenticated endpoints today. | E7: 6 | F7: 2 | G7: 2 | H7: 18 | I7: =COUNTIFS(Findings!$B$2:$B$91,$A7,Findings!$Q$2:$Q$91,"Done") | J7: =IF($E7=0,0,$I7/$E7)
A8: E7 | B8: Third-Party Dependency & Cost Control | C8: Every external dependency is licensed, rate-limited and budgeted for 100k users. | D8: OSM tiles, Nominatim geocoding and Gemini are all used in ways their terms forbid at this volume, with no cost ceiling. | E8: 4 | F8: 2 | G8: 2 | H8: 15 | I8: =COUNTIFS(Findings!$B$2:$B$91,$A8,Findings!$Q$2:$Q$91,"Done") | J8: =IF($E8=0,0,$I8/$E8)
A9: E8 | B9: Mobile App Production Readiness | C9: The Flutter app is observable, secure on-device, resilient offline and cheap on data. | D9: No crash reporting, plaintext local storage, no offline cache, uncapped uploads. | E9: 9 | F9: 1 | G9: 4 | H9: 21 | I9: =COUNTIFS(Findings!$B$2:$B$91,$A9,Findings!$Q$2:$Q$91,"Done") | J9: =IF($E9=0,0,$I9/$E9)
A10: E9 | B10: Admin Dashboard for Scale | C10: Server-side querying, real data, and per-office accountability in the console. | D10: The console is a demo: it loads everything client-side and renders mock social-media analytics about named real politicians. | E10: 5 | F10: 1 | G10: 3 | H10: 22 | I10: =COUNTIFS(Findings!$B$2:$B$91,$A10,Findings!$Q$2:$Q$91,"Done") | J10: =IF($E10=0,0,$I10/$E10)
A11: E10 | B11: Operations, Release & Quality Engineering | C11: Backups, migrations, CI, load testing and a rollback path before go-live. | D11: There is no test suite for the backend, no migration tool, no backup policy and no load test evidence. | E11: 8 | F11: 4 | G11: 1 | H11: 30 | I11: =COUNTIFS(Findings!$B$2:$B$91,$A11,Findings!$Q$2:$Q$91,"Done") | J11: =IF($E11=0,0,$I11/$E11)

Sheet Sprints
A1: Sprint | B1: Name | C1: Theme | D1: Weeks | E1: Entry criteria | F1: Findings | G1: Critical | H1: Effort (days) | I1: Done | J1: % complete | K1: Exit criteria
A2: S1 | B2: Stop the Bleeding — Security | C2: Close every unauthenticated write and PII leak. Nothing else ships first. | D2: 2 | E2: Audit signed off. Staging environment available. | F2: 11 | G2: 7 | H2: 24 | I2: =COUNTIFS(Findings!$C$2:$C$91,$A2,Findings!$Q$2:$Q$91,"Done") | J2: =IF($F2=0,0,$I2/$F2) | K2: No unauthenticated write path remains; no public endpoint returns a phone number, name or account id.
A3: S2 | B3: Auth Foundation | C3: Real tokens for citizen, coordinator and admin; server-side rate limiting. | D3: 2 | E3: S1 merged. Token scheme agreed. | F3: 8 | G3: 5 | H3: 19 | I3: =COUNTIFS(Findings!$C$2:$C$91,$A3,Findings!$Q$2:$Q$91,"Done") | J3: =IF($F3=0,0,$I3/$F3) | K3: Every client holds a real token; OTP is throttled and never returned in a response; no plaintext password remains in the database.
A4: S3 | B4: Data Platform Migration | C4: PostgreSQL + PostGIS, indexes, migrations, backups. | D4: 3 | E4: Schema frozen. Data migration script reviewed. | F4: 9 | G4: 4 | H4: 35 | I4: =COUNTIFS(Findings!$C$2:$C$91,$A4,Findings!$Q$2:$Q$91,"Done") | J4: =IF($F4=0,0,$I4/$F4) | K4: Production runs on PostgreSQL with indexes in place, Alembic migrations, verified nightly backups and a rehearsed restore.
A5: S4 | B5: API Scale Hardening | C5: Pagination, indexed queries, async offload of Gemini, caching. | D5: 3 | E5: S3 live in staging. | F5: 21 | G5: 7 | H5: 55 | I5: =COUNTIFS(Findings!$C$2:$C$91,$A5,Findings!$Q$2:$Q$91,"Done") | J5: =IF($F5=0,0,$I5/$F5) | K5: Every list endpoint is paginated; no endpoint scans the issues table; report submission returns in under 500ms with AI work offloaded.
A6: S5 | B6: Realtime & Notification Rework | C6: Push-first delivery, retention, batching, FCM correctness. | D6: 2 | E6: S2 tokens available for push auth. | F6: 6 | G6: 2 | H6: 17 | I6: =COUNTIFS(Findings!$C$2:$C$91,$A6,Findings!$Q$2:$Q$91,"Done") | J6: =IF($F6=0,0,$I6/$F6) | K6: Push is the primary delivery channel; client polling load is reduced by at least 95%; dead tokens are pruned.
A7: S6 | B7: Multi-Tenancy Rollout | C7: Statewide boundaries, per-AC scoping, per-office admin accounts. | D7: 3 | E7: S2 and S3 complete. | F7: 6 | G7: 3 | H7: 40 | I7: =COUNTIFS(Findings!$C$2:$C$91,$A7,Findings!$Q$2:$Q$91,"Done") | J7: =IF($F7=0,0,$I7/$F7) | K7: Statewide boundaries load; a second constituency is onboarded end to end with data isolation proven by test.
A8: S7 | B8: Mobile Production Readiness | C8: Crash reporting, secure storage, offline cache, upload caps. | D8: 2 | E8: S2 tokens integrated in the app. | F8: 10 | G8: 1 | H8: 22 | I8: =COUNTIFS(Findings!$C$2:$C$91,$A8,Findings!$Q$2:$Q$91,"Done") | J8: =IF($F8=0,0,$I8/$F8) | K8: Crash reporting live with a baseline crash-free rate; session data in secure storage; upload caps enforced; boundaries cached on disk.
A9: S8 | B9: Admin Dashboard Rebuild | C9: Server-side queries, real analytics, audit trail per operator. | D9: 3 | E9: S4 pagination endpoints available. | F9: 8 | G9: 2 | H9: 34 | I9: =COUNTIFS(Findings!$C$2:$C$91,$A9,Findings!$Q$2:$Q$91,"Done") | J9: =IF($F9=0,0,$I9/$F9) | K9: Console loads in under 2 seconds against 100k seeded grievances; no mock analytics reachable; every action attributed to an operator.
A10: S9 | B10: Compliance & Cost | C10: DPDP posture, retention, licensed map/geocode/LLM budgets. | D10: 2 | E10: Legal review booked. Vendor quotes in. | F10: 6 | G10: 4 | H10: 25 | I10: =COUNTIFS(Findings!$C$2:$C$91,$A10,Findings!$Q$2:$Q$91,"Done") | J10: =IF($F10=0,0,$I10/$F10) | K10: Licensed tile and geocoding providers live with budgets; DPDP retention, export and erasure implemented; AI spend capped per tenant.
A11: S10 | B11: Load Test & Launch Readiness | C11: Prove 100k concurrent-capable, runbooks, rollback. | D11: 2 | E11: All prior sprints merged to staging. | F11: 5 | G11: 3 | H11: 25 | I11: =COUNTIFS(Findings!$C$2:$C$91,$A11,Findings!$Q$2:$Q$91,"Done") | J11: =IF($F11=0,0,$I11/$F11) | K11: Load test sustains target concurrency within SLO; runbooks and rollback rehearsed; launch go/no-go signed off.

Sheet Scale Maths
B2: Why the current design does not reach the target
B3: Order-of-magnitude arithmetic behind the Critical scalability findings. Assumptions are stated so they can be argued with.
B5: Measure | C5: Today | D5: At target | E5: Consequence
B6: Notification polling requests/second | C6: ~0 (demo users) | D6: ~11,700 rps | E6: Two independent pollers per device at 15s and 20s. 100,000 devices produce roughly 6,700 + 5,000 requests per second of pure overhead, against a single SQLite file, before any citizen action. See F045, F046.
B7: Rows scanned per map open | C7: 1,020 | D7: 100,000+ | E7: /api/issues/nearby loads every non-SUBMITTED row and computes Haversine in Python per row. The map is the landing screen, so this is the hottest path in the product. See F028.
B8: Admin console payload per page load | C8: ~1 MB | D8: several hundred MB | E8: The console fetches the entire issues table with no pagination and filters client-side. The browser will not survive it. See F027, F076.
B9: Full table scans per dashboard open | C9: ~5 | D9: ~500 | E9: coordinator-performance runs one scan per coordinator. 100 offices at roughly 5 coordinators each. See F031.
B10: Ticket-number collision probability | C10: negligible | D10: ~69% at 100k, effectively certain beyond | E10: 8 hex characters is a 2^32 space with no UNIQUE constraint. Two citizens receive the same tracking number. See F021.
B11: Constituencies the system can serve | C11: 16 (Chennai only) | D11: 100 required | E11: Boundaries are Greater Chennai Corporation only and reports outside them are refused with a 422. 99 of 100 target offices cannot receive a grievance. See F051, F052, F089.
B12: Gemini invocations per grievance | C12: up to 12 | D12: up to 12, unbudgeted | E12: Three sequential calls, each with two attempts across two models, with no per-tenant quota or spend cap. See F042, F066.
B13: OSM tile requests/day | C13: low | D13: millions | E13: The OSM Foundation tile policy forbids distributing an app that uses its tiles. Traffic at this volume will be blocked and every map goes blank. See F063.
B14: Nominatim geocode requests/day | C14: low | D14: hundreds of thousands | E14: Policy caps absolute maximum use at 1 request per second. Called directly from every handset and again server-side per report. See F064, F065.
B15: Concurrent database writers | C15: 1 | D15: 1 | E15: SQLite serialises writes behind a global lock and the deployment is a single process. Neither the engine nor the topology can be scaled out without the Postgres migration. See F018, F083.
